oreiller/__init__.py
oreiller/oreiller.py
oreiller-0.2.0.dist-info/LICENSE
oreiller-0.2.0.dist-info/METADATA
oreiller-0.2.0.dist-info/WHEEL
oreiller-0.2.0.dist-info/top_level.txt
oreiller-0.2.0.dist-info/RECORD
