Metadata-Version: 2.1
Name: oreiller
Version: 0.2.0
Summary: The package for easy and convenient image manipulation, heavy use of Pillow
Home-page: https://github.com/Abdur-RahmaanJ/oreiller
Author: Abdur-Rahmaan Janhangeer
Author-email: arj.python@gmail.com
Project-URL: Bug Reports, https://github.com/Abdur-RahmaanJ/oreiller/issues
Project-URL: Source, https://github.com/Abdur-RahmaanJ/oreiller/
Keywords: image pillow
Classifier: Development Status :: 3 - Alpha
Classifier: Intended Audience :: Developers
Classifier: License :: OSI Approved :: MIT License
Classifier: Programming Language :: Python :: 3.7
Classifier: Programming Language :: Python :: 3.8
Classifier: Programming Language :: Python :: 3.9
Classifier: Programming Language :: Python :: 3.10
Classifier: Programming Language :: Python :: 3.10
Classifier: Programming Language :: Python :: 3.11
Requires-Python: >=3.7
License-File: LICENSE
Requires-Dist: pillow
Requires-Dist: pilmoji
